message_sdk/__init__.py
message_sdk/common/enums.py
message_sdk/message_sdk.py
message_sdk-0.0.2.dist-info/METADATA
message_sdk-0.0.2.dist-info/WHEEL
message_sdk-0.0.2.dist-info/RECORD
